denden_extension.py
denden_extension-2.0.0.dist-info/LICENSE
denden_extension-2.0.0.dist-info/METADATA
denden_extension-2.0.0.dist-info/WHEEL
denden_extension-2.0.0.dist-info/top_level.txt
denden_extension-2.0.0.dist-info/RECORD
