Metadata-Version: 2.1
Name: denden-extension
Version: 2.0.0
Summary: Python-Markdown extension for DenDenMarkdown
Home-page: https://github.com/muranamihdk/denden_extension
Author: Hideaki Muranami
License: MIT
Keywords: Python-Markdown DenDenMarkdown DTP epub typesetting Japanese ruby でんでんマークダウン 電子出版 電子書籍 組版 日本語 ルビ
Platform: UNKNOWN
Classifier: Development Status :: 5 - Production/Stable
Classifier: License :: OSI Approved :: MIT License
Classifier: Operating System :: OS Independent
Classifier: Intended Audience :: Developers
Classifier: Natural Language :: Japanese
Classifier: Topic :: Text Processing :: Filters
Classifier: Topic :: Text Processing :: Markup
Classifier: Topic :: Text Processing :: Markup :: HTML
Classifier: Topic :: Text Processing :: Markup :: Markdown
Classifier: Programming Language :: Python :: 3
Classifier: Programming Language :: Python :: 3.4
Classifier: Programming Language :: Python :: 3.5
Classifier: Programming Language :: Python :: 3.9
Requires-Python: >=3
Requires-Dist: markdown (<3.1,>=3.0.0)
